dependecymanager/__init__.py
dependecymanager/__main__.py
dependecymanager/dmexceptions.py
dependecymanager/dmutils.py
dependecymanager/tree.py
dependecymanager/utils.py
dependencymanager-1.0.0.dist-info/LICENSE
dependencymanager-1.0.0.dist-info/METADATA
dependencymanager-1.0.0.dist-info/WHEEL
dependencymanager-1.0.0.dist-info/top_level.txt
dependencymanager-1.0.0.dist-info/RECORD
