Metadata-Version: 2.1
Name: dependencymanager
Version: 1.0.0
Summary: An easy way to manage development and procution dependecies.
Home-page: https://github.com/davincif/dependency_manager
Author: davincif
Author-email: davincif@davincif.com
License: UNKNOWN
Project-URL: Bug Reports, https://github.com/davincif/dependency_manager/issues
Project-URL: Source, https://github.com/davincif/dependency_manager/
Keywords: package management manager pypi version development
Platform: UNKNOWN
Classifier: Development Status :: 5 - Production/Stable
Classifier: Intended Audience :: Developers
Classifier: Topic :: Software Development
Classifier: Topic :: Software Development :: Build Tools
Classifier: License :: OSI Approved :: zlib/libpng License
Classifier: Programming Language :: Python :: 3.6
Classifier: Programming Language :: Python :: 3.7
Classifier: Programming Language :: Python :: 3.8
Requires-Python: >=3.6
